Metadata-Version: 1.1
Name: vcp-beuth
Version: 0.0.1
Summary: Project Description
Home-page: UNKNOWN
Author: s74593 <s74593@beuth-hochschule.de>
Author-email: UNKNOWN
License: MIT
Platform: UNKNOWN
Classifier: Framework :: Dash
